girder_slicer_cli_web-1.5.14.dist-info/licenses/LICENSE
slicer_cli_web/__init__.py
slicer_cli_web/cli_list_entrypoint.py
slicer_cli_web/cli_utils.py
slicer_cli_web/config.py
slicer_cli_web/ctk_cli_adjustment.py
slicer_cli_web/docker_resource.py
slicer_cli_web/girder_plugin.py
slicer_cli_web/image_job.py
slicer_cli_web/prepare_task.py
slicer_cli_web/rest_slicer_cli.py
slicer_cli_web/worker_tools.py
slicer_cli_web/girder_worker_plugin/__init__.py
slicer_cli_web/girder_worker_plugin/cli_progress.py
slicer_cli_web/girder_worker_plugin/direct_docker_run.py
slicer_cli_web/models/__init__.py
slicer_cli_web/models/docker_image.py
slicer_cli_web/models/exceptions.py
slicer_cli_web/models/json_to_xml.py
slicer_cli_web/models/parser.py
slicer_cli_web/models/schema.json
slicer_cli_web/web_client/JobStatus.js
slicer_cli_web/web_client/events.js
slicer_cli_web/web_client/index.js
slicer_cli_web/web_client/main.js
slicer_cli_web/web_client/package.json
slicer_cli_web/web_client/routes.js
slicer_cli_web/web_client/utils.js
slicer_cli_web/web_client/collections/WidgetCollection.js
slicer_cli_web/web_client/collections/index.js
slicer_cli_web/web_client/models/WidgetModel.js
slicer_cli_web/web_client/models/index.js
slicer_cli_web/web_client/parser/constraints.js
slicer_cli_web/web_client/parser/convert.js
slicer_cli_web/web_client/parser/defaultValue.js
slicer_cli_web/web_client/parser/group.js
slicer_cli_web/web_client/parser/index.js
slicer_cli_web/web_client/parser/panel.js
slicer_cli_web/web_client/parser/param.js
slicer_cli_web/web_client/parser/parse.js
slicer_cli_web/web_client/parser/widget.js
slicer_cli_web/web_client/stylesheets/configView.styl
slicer_cli_web/web_client/stylesheets/controlWidget.styl
slicer_cli_web/web_client/stylesheets/controlsPanel.styl
slicer_cli_web/web_client/stylesheets/outputParameterDialog.styl
slicer_cli_web/web_client/stylesheets/panel.styl
slicer_cli_web/web_client/stylesheets/panelGroup.styl
slicer_cli_web/web_client/stylesheets/slicerUI.styl
slicer_cli_web/web_client/templates/booleanWidget.pug
girder_slicer_cli_web-1.5.14.dist-info/METADATA
girder_slicer_cli_web-1.5.14.dist-info/WHEEL
girder_slicer_cli_web-1.5.14.dist-info/entry_points.txt
girder_slicer_cli_web-1.5.14.dist-info/top_level.txt
girder_slicer_cli_web-1.5.14.dist-info/RECORD
