Metadata-Version: 2.4
Name: girder-slicer-cli-web
Version: 1.5.14
Summary: A girder plugin for exposing slicer CLIs over the web
Home-page: https://github.com/girder/slicer_cli_web
Author: Kitware, Inc.
Author-email: kitware@kitware.com
License: Apache Software License 2.0
Keywords: girder-plugin,slicer_cli_web
Classifier: Development Status :: 5 - Production/Stable
Classifier: Environment :: Web Environment
Classifier: License :: OSI Approved :: Apache Software License
Classifier: Operating System :: OS Independent
Classifier: Programming Language :: Python
Classifier: Programming Language :: Python :: 3
Classifier: Programming Language :: Python :: 3.8
Classifier: Programming Language :: Python :: 3.9
Classifier: Programming Language :: Python :: 3.10
Classifier: Programming Language :: Python :: 3.11
Classifier: Programming Language :: Python :: 3.12
Classifier: Programming Language :: Python :: 3.13
Requires-Python: >=3.8
License-File: LICENSE
Requires-Dist: ctk_cli
Requires-Dist: jinja2
Requires-Dist: jsonschema
Requires-Dist: pyyaml
Provides-Extra: girder
Requires-Dist: docker>=2.6.0; extra == "girder"
Requires-Dist: girder>=3.0.4; extra == "girder"
Requires-Dist: girder-jobs>=3.0.3; extra == "girder"
Requires-Dist: girder-worker[girder]>=0.6.0; extra == "girder"
Provides-Extra: worker
Requires-Dist: docker>=2.6.0; extra == "worker"
Requires-Dist: girder-worker[worker]>=0.6.0; extra == "worker"
Dynamic: author
Dynamic: author-email
Dynamic: classifier
Dynamic: description
Dynamic: description-content-type
Dynamic: home-page
Dynamic: keywords
Dynamic: license
Dynamic: license-file
Dynamic: provides-extra
Dynamic: requires-dist
Dynamic: requires-python
Dynamic: summary
